.coveragerc
.gitlab-ci.yml
AUTHORS.rst
INSTALL.rst
LICENSE.rst
MANIFEST.in
README.rst
changelog.txt
conftest.py
environment.yml
pytest.ini
setup.cfg
setup.py
doc/Makefile
doc/kwantdoctheme/theme.conf
doc/kwantdoctheme/static/kwantdoctheme.css
doc/material/adaptive_solver.ai
doc/material/figures_junction_circuit_and_quantum_part.svg
doc/material/make_figure_timescale_decoupling.py
doc/source/conf.py
doc/source/index.rst
doc/source/_static/kwant.css
doc/source/_static/kwant_logo.png
doc/source/_static/mathconf.js
doc/source/_static/sidebar.js
doc/source/_static/togglediv.js
doc/source/extensions/index.rst
doc/source/pre/about.rst
doc/source/pre/authors.rst
doc/source/pre/cite.rst
doc/source/pre/index.rst
doc/source/pre/installation.rst
doc/source/pre/license.rst
doc/source/pre/whats_new.rst
doc/source/reference/index.rst
doc/source/reference/tkwant.integrate.rst
doc/source/reference/tkwant.leads.rst
doc/source/reference/tkwant.logging.rst
doc/source/reference/tkwant.manybody.rst
doc/source/reference/tkwant.mpi.rst
doc/source/reference/tkwant.onebody.kernel.rst
doc/source/reference/tkwant.onebody.rst
doc/source/reference/tkwant.onebody.solvers.rst
doc/source/reference/tkwant.rst
doc/source/reference/tkwant.system.rst
doc/source/tutorial/common.py
doc/source/tutorial/index.rst
doc/sphinxext/kwantdoc.py
doc/templates/layout.html
doc/templates/autosummary/class.rst
doc/tutorial_source/1d_chain_closed.png
doc/tutorial_source/1d_chain_open.png
doc/tutorial_source/1d_wire_high_level.py
doc/tutorial_source/1d_wire_low_level.py
doc/tutorial_source/1d_wire_onsite.py
doc/tutorial_source/adaptive_solver_sketch.png
doc/tutorial_source/alternative_boundary_conditions.py
doc/tutorial_source/alternative_boundary_conditions.rst
doc/tutorial_source/bdg_junction_plot_results.py
doc/tutorial_source/bdg_junction_run_computation.py
doc/tutorial_source/bdg_junction_vj_vs_time.png
doc/tutorial_source/boundary_condition.rst
doc/tutorial_source/boundstates.rst
tkwant.egg-info/PKG-INFO
tkwant.egg-info/SOURCES.txt
tkwant.egg-info/dependency_links.txt
tkwant.egg-info/requires.txt
tkwant.egg-info/top_level.txt
