Metadata-Version: 1.1
Name: tkwant
Version: 1.1.0
Summary: Package for time-dependent quantum transport simulations
Home-page: https://tkwant.kwant-project.org/
Author: tkwant authors
Author-email: tkwant-authors@kwant-project.org
License: BSD
Platform: Unix
Platform: Linux
Platform: Mac OS-X
Platform: Windows
Classifier: Development Status :: 5 - Production/Stable
Classifier: Intended Audience :: Science/Research
Classifier: Programming Language :: Python :: 3 :: Only
Classifier: Topic :: Scientific/Engineering
Classifier: Topic :: Scientific/Engineering :: Physics
Classifier: Operating System :: POSIX
Classifier: Operating System :: Unix
Classifier: Operating System :: MacOS :: MacOS X
Classifier: Operating System :: Microsoft :: Windows
